libname/__init__.py
libname/mickzaa.py
youngoldlib/__init__.py
youngoldlib/mickzaa.py
youngold-2.0.0.dist-info/LICENSE
youngold-2.0.0.dist-info/METADATA
youngold-2.0.0.dist-info/WHEEL
youngold-2.0.0.dist-info/top_level.txt
youngold-2.0.0.dist-info/RECORD
