Metadata-Version: 2.1
Name: youngold
Version: 2.0.0
Summary: Compare age with mickzaa
Home-page: UNKNOWN
Author: NeuralNine (Florian Dedov)
Author-email: <arceus@hotmail.com>
License: UNKNOWN
Keywords: python
Platform: UNKNOWN
Classifier: Development Status :: 1 - Planning
Classifier: Intended Audience :: Developers
Classifier: Programming Language :: Python :: 3
Classifier: Operating System :: Unix
Classifier: Operating System :: MacOS :: MacOS X
Classifier: Operating System :: Microsoft :: Windows
License-File: LICENSE
